turborocket/__init__.py
turborocket/characteristic/__init__.py
turborocket/characteristic/turbo_characteristic.py
turborocket/combustion/__init__.py
turborocket/combustion/comb_solver.py
turborocket/fluids/__init__.py
turborocket/fluids/fluids.py
turborocket/profiling/__init__.py
turborocket/profiling/Supersonic/__init__.py
turborocket/profiling/Supersonic/circular.py
turborocket/profiling/Supersonic/constraints.py
turborocket/profiling/Supersonic/fixed_edge.py
turborocket/profiling/Supersonic/supersonic_profile.py
turborocket/profiling/Supersonic/transition.py
turborocket/sizing/__init__.py
turborocket/sizing/pump.py
turborocket/sizing/tubing.py
turborocket/solvers/__init__.py
turborocket/solvers/solver.py
turborocket/tools/__init__.py
turborocket/tools/loaders.py
turborocket/transient/__init__.py
turborocket/transient/start_up.py
turborocket-0.0.2.dist-info/licenses/LICENSE
turborocket-0.0.2.dist-info/METADATA
turborocket-0.0.2.dist-info/WHEEL
turborocket-0.0.2.dist-info/top_level.txt
turborocket-0.0.2.dist-info/RECORD
